{
    "features": {
        "path": "hh/dump/configs/features.json"
    },
    "samples": [
        {
            "label": "4b_mc21_ggF_k01",
            "class_label": "label_HH",
            "selections": {
                "jets": {
                    "pt": {
                        "operator": ">",
                        "value": 40000
                    },
                    "eta": {
                        "operator": "<",
                        "value": 2.5
                    },
                    "count": {
                        "operator": ">=",
                        "value": 4
                    },
                    "btagging": {
                        "model": "DL1dv01",
                        "efficiency": 0.85,
                        "count": {
                            "operator": ">=",
                            "value": 4
                        }
                    }
                }
            },
            "paths": [
                "/lustre/fs22/group/atlas/ruelasv/samples/mc21_13p6TeV.hh4b.ggF/output/user.viruelas.EJ_2023_05_30.601479.PhPy8EG_HH4b_cHHH01d0.e8472_s3873_r13829_p5631_TREE/"
            ],
            "metadata": [
                {
                    "logicalDatasetName": "mc21_13p6TeV.601479.PhPy8EG_HH4b_cHHH01d0.deriv.DAOD_PHYS.e8472_s3873_r13829_p5631",
                    "genFiltEff": 1,
                    "crossSection": 0.000030836,
                    "kFactor": 1.0,
                    "luminosity": 1.0
                }
            ]
        }
    ]
}